emailmasterpt/__init__.py
emailmasterpt/agendador.py
emailmasterpt/core.py
emailmasterpt/excecoes.py
emailmasterpt/provedores.py
emailmasterpt/utils.py
emailmasterpt-1.0.0.dist-info/licenses/LICENSE
emailmasterpt-1.0.0.dist-info/METADATA
emailmasterpt-1.0.0.dist-info/WHEEL
emailmasterpt-1.0.0.dist-info/top_level.txt
emailmasterpt-1.0.0.dist-info/RECORD
